data_job_etl/.ipynb_checkpoints/rank-checkpoint.py
data_job_etl/__init__.py
data_job_etl/build_technos.py
data_job_etl/config/definitions.py
data_job_etl/config/etl_logger.py
data_job_etl/config/postgres_schema.py
data_job_etl/credentials.json
data_job_etl/data/__init__.py
data_job_etl/data/mad2023.json
data_job_etl/etl.py
data_job_etl/extract/extract.py
data_job_etl/file.log
data_job_etl/load/create_tables.py
data_job_etl/load/load.py
data_job_etl/message.py
data_job_etl/rank.py
data_job_etl/recommendation_system.py
data_job_etl/summarise.py
data_job_etl/transform/file.log
data_job_etl/transform/preprocess.py
data_job_etl/transform/process.py
data_job_etl/update_table.py
data_job_etl-1.1.4.dist-info/METADATA
data_job_etl-1.1.4.dist-info/WHEEL
data_job_etl-1.1.4.dist-info/RECORD
