Metadata-Version: 2.1
Name: data-job-etl
Version: 1.1.4
Summary: 
Author: Donor
Author-email: donorfelita@msn.com
Requires-Python: >=3.9,<4.0
Classifier: Programming Language :: Python :: 3
Classifier: Programming Language :: Python :: 3.9
Classifier: Programming Language :: Python :: 3.10
Classifier: Programming Language :: Python :: 3.11
Requires-Dist: SQLAlchemy (>=2.0.0,<2.1.0)
Requires-Dist: pandas (>=1.4.3,<2.0.0)
Requires-Dist: psycopg2 (>=2.9.3,<3.0.0)
